MANIFEST.in
README.md
requirements.txt
setup.cfg
setup.py
hedgedata/__init__.py
hedgedata/backfill.py
hedgedata/cache.py
hedgedata/data.py
hedgedata/data_utils.py
hedgedata/define.py
hedgedata/distributor.py
hedgedata/etf.py
hedgedata/fetch.py
hedgedata/log_utils.py
hedgedata/options.py
hedgedata/transform.py
hedgedata/utils.py
hedgedata/validate.py
hedgedata.egg-info/PKG-INFO
hedgedata.egg-info/SOURCES.txt
hedgedata.egg-info/dependency_links.txt
hedgedata.egg-info/not-zip-safe
hedgedata.egg-info/requires.txt
hedgedata.egg-info/top_level.txt