Metadata-Version: 1.1
Name: hedgedata
Version: 0.0.2
Summary: Financial Analytics
Home-page: https://github.com/timkpaine/hedgedata
Author: Tim Paine
Author-email: timothy.k.paine@gmail.com
License: BSD 3 Clause
Download-URL: https://github.com/timkpaine/hedgedata/archive/v0.0.2.tar.gz
Keywords: realtime financial Analytics
Platform: UNKNOWN
Classifier: Development Status :: 3 - Alpha
Classifier: Programming Language :: Python :: 2
Classifier: Programming Language :: Python :: 2.7
Classifier: Programming Language :: Python :: 3
Classifier: Programming Language :: Python :: 3.3
Classifier: Programming Language :: Python :: 3.4
Classifier: Programming Language :: Python :: 3.5
Classifier: Programming Language :: Python :: 3.6
Classifier: Programming Language :: Python :: 3.7
